harmon/__init__.py
harmon/context_filler.py
harmon/dataset.py
harmon/generate.py
harmon/tokenizer.py
harmon/train.py
harmon/utils.py
harmon-0.2.0.dist-info/LICENSE
harmon-0.2.0.dist-info/METADATA
harmon-0.2.0.dist-info/WHEEL
harmon-0.2.0.dist-info/RECORD
