Metadata-Version: 2.1
Name: harmon
Version: 0.2.0
Summary: A chess engine that considers human mistakes
Home-page: https://github.com/khoda81/harmon
License: MIT
Author: Mahdi Khodabandeh
Author-email: 20.mahdikh.0@gmail.com
Requires-Python: >=3.9,<4.0
Classifier: Development Status :: 3 - Alpha
Classifier: Environment :: Console
Classifier: Framework :: Pytest
Classifier: Intended Audience :: Developers
Classifier: License :: OSI Approved :: MIT License
Classifier: Natural Language :: English
Classifier: Operating System :: OS Independent
Classifier: Programming Language :: Python
Classifier: Programming Language :: Python :: 3
Classifier: Programming Language :: Python :: 3.9
Classifier: Programming Language :: Python :: 3.10
Classifier: Programming Language :: Python :: 3.11
Classifier: Topic :: Games/Entertainment :: Board Games
Classifier: Topic :: Scientific/Engineering :: Artificial Intelligence
Requires-Dist: attrs (>=23.1.0,<24.0.0)
Requires-Dist: bidict (>=0.22.1)
Requires-Dist: more-itertools (>=10.1.0,<11.0.0)
Requires-Dist: python-chess (>=1.999,<2.0)
Requires-Dist: torch (==1.12.1)
Requires-Dist: zstandard (>=0.21.0,<0.22.0)
Project-URL: Repository, https://github.com/khoda81/harmon
